rabbitmq/__init__.py
rabbitmq-0.1.0.dist-info/DESCRIPTION.rst
rabbitmq-0.1.0.dist-info/METADATA
rabbitmq-0.1.0.dist-info/RECORD
rabbitmq-0.1.0.dist-info/WHEEL
rabbitmq-0.1.0.dist-info/metadata.json
rabbitmq-0.1.0.dist-info/top_level.txt
